llamadatasets/__init__.py
llamadatasets/core/__init__.py
llamadatasets/core/dataloader.py
llamadatasets/core/dataset.py
llamadatasets/core/streaming.py
llamadatasets/generators/__init__.py
llamadatasets/generators/text.py
llamadatasets/splitters/__init__.py
llamadatasets/splitters/base.py
llamadatasets/transformers/__init__.py
llamadatasets/transformers/base.py
llamadatasets/transformers/text.py
llamadatasets_llamasearch-0.1.0.dist-info/licenses/LICENSE
llamadatasets_llamasearch-0.1.0.dist-info/METADATA
llamadatasets_llamasearch-0.1.0.dist-info/WHEEL
llamadatasets_llamasearch-0.1.0.dist-info/top_level.txt
llamadatasets_llamasearch-0.1.0.dist-info/RECORD
