Metadata-Version: 2.4
Name: llamadatasets-llamasearch
Version: 0.1.0
Summary: Dataset management and processing library for LlamaSearch.ai applications
Home-page: https://llamasearch.ai
Author: LlamaSearch AI
Author-email: nikjois@llamasearch.ai
Project-URL: Bug Tracker, https://github.com/llamasearch/llamadatasets/issues
Project-URL: Documentation, https://docs.llamasearch.ai/llamadatasets
Classifier: Programming Language :: Python :: 3
Classifier: Programming Language :: Python :: 3.8
Classifier: Programming Language :: Python :: 3.9
Classifier: Programming Language :: Python :: 3.10
Classifier: Programming Language :: Python :: 3.11
Classifier: License :: OSI Approved :: MIT License
Classifier: Operating System :: OS Independent
Classifier: Development Status :: 4 - Beta
Classifier: Intended Audience :: Developers
Classifier: Topic :: Software Development :: Libraries :: Python Modules
Classifier: Topic :: Scientific/Engineering :: Artificial Intelligence
Requires-Python: >=3.8
License-File: LICENSE
Requires-Dist: numpy>=1.19.0
Requires-Dist: pandas>=1.3.0
Requires-Dist: pyarrow>=5.0.0
Requires-Dist: tqdm>=4.61.0
Requires-Dist: pydantic>=1.8.0
Requires-Dist: sqlalchemy>=1.4.0
Requires-Dist: scikit-learn>=1.0.0
Requires-Dist: fsspec>=2021.10.0
Requires-Dist: smart-open>=5.0.0
Requires-Dist: typing-extensions>=3.10.0
Provides-Extra: dev
Requires-Dist: pytest>=6.0.0; extra == "dev"
Requires-Dist: pytest-cov>=2.12.0; extra == "dev"
Requires-Dist: black>=21.5b2; extra == "dev"
Requires-Dist: flake8>=3.9.2; extra == "dev"
Requires-Dist: mypy>=0.812; extra == "dev"
Requires-Dist: isort>=5.9.1; extra == "dev"
Requires-Dist: tox>=3.24.0; extra == "dev"
Provides-Extra: nlp
Requires-Dist: nltk>=3.6.0; extra == "nlp"
Requires-Dist: spacy>=3.0.0; extra == "nlp"
Requires-Dist: transformers>=4.5.0; extra == "nlp"
Provides-Extra: images
Requires-Dist: pillow>=8.2.0; extra == "images"
Requires-Dist: torchvision>=0.10.0; extra == "images"
Provides-Extra: docs
Requires-Dist: sphinx>=4.0.2; extra == "docs"
Requires-Dist: sphinx-rtd-theme>=0.5.2; extra == "docs"
Requires-Dist: sphinx-autodoc-typehints>=1.12.0; extra == "docs"
Dynamic: author
Dynamic: author-email
Dynamic: classifier
Dynamic: description
Dynamic: description-content-type
Dynamic: home-page
Dynamic: license-file
Dynamic: project-url
Dynamic: provides-extra
Dynamic: requires-dist
Dynamic: requires-python
Dynamic: summary
